tap_circle_ci/__init__.py
tap_circle_ci/__main__.py
tap_circle_ci/client.py
tap_circle_ci/schemas/__init__.py
tap_circle_ci/schemas/jobs.json
tap_circle_ci/schemas/pipelines.json
tap_circle_ci/schemas/workflows.json
tap_circle_ci/streams.py
tap_circle_ci/tap.py
meltano_tap_circle_ci-0.6.2.dist-info/METADATA
meltano_tap_circle_ci-0.6.2.dist-info/WHEEL
meltano_tap_circle_ci-0.6.2.dist-info/entry_points.txt
meltano_tap_circle_ci-0.6.2.dist-info/licenses/LICENSE
meltano_tap_circle_ci-0.6.2.dist-info/RECORD
