Metadata-Version: 2.4
Name: meltano-tap-circle-ci
Version: 0.6.2
Summary: Singer tap for CircleCI, built with the Meltano SDK for Singer Taps.
License: Apache-2.0
License-File: LICENSE
Keywords: ELT,Meltano,CircleCI
Author: Fran Lozano
Author-email: fjlozanos@gmail.com
Maintainer: Meltano Team
Maintainer-email: hello@meltano.com
Requires-Python: >=3.10
Classifier: License :: OSI Approved :: Apache Software License
Classifier: Programming Language :: Python :: 3
Classifier: Programming Language :: Python :: 3.10
Classifier: Programming Language :: Python :: 3.11
Classifier: Programming Language :: Python :: 3.12
Classifier: Programming Language :: Python :: 3.13
Classifier: Programming Language :: Python :: 3.14
Requires-Dist: requests (>=2.32.1,<2.33.0)
Requires-Dist: singer-sdk (>=0.52.0,<0.53.0)
Project-URL: Documentation, https://github.com/MeltanoLabs/tap-circle-ci/blob/main/README.md
Project-URL: Homepage, https://github.com/MeltanoLabs/tap-circle-ci
Project-URL: Repository, https://github.com/MeltanoLabs/tap-circle-ci
